darlog_pypi/__init__.py
darlog_pypi-1.0.0.dist-info/LICENSE.md
darlog_pypi-1.0.0.dist-info/METADATA
darlog_pypi-1.0.0.dist-info/WHEEL
darlog_pypi-1.0.0.dist-info/top_level.txt
darlog_pypi-1.0.0.dist-info/RECORD
