Metadata-Version: 2.1
Name: darlog-pypi
Version: 1.0.0
Summary: Lex Darlog's tools library automating packages publication to pypi.org
Home-page: https://github.com/Lex-DRL/darlog-pypi
Author: Lex Darlog (Lex-DRL)
Maintainer: Lex Darlog (Lex-DRL)
License: LGPL-3.0-or-later
Keywords: utility,pypi,publishing,setuptools,pip
Platform: UNKNOWN
Classifier: Development Status :: 5 - Production/Stable
Classifier: Intended Audience :: Developers
Classifier: License :: OSI Approved :: GNU Lesser General Public License v3 or later (LGPLv3+)
Classifier: Natural Language :: English
Classifier: Operating System :: OS Independent
Classifier: Programming Language :: Python
Classifier: Programming Language :: Python :: 2
Classifier: Programming Language :: Python :: 2.7
Classifier: Programming Language :: Python :: 3
Classifier: Topic :: Software Development :: Libraries :: Python Modules
Classifier: Typing :: Typed
Requires-Python: >=2.7
Provides-Extra: dev
